{
  "timestamp": "2025-05-23 08:10:35",
  "symbols": {
    "BTCUSDT": {
      "price_change": 1.3206,
      "oi_change": -0.5882,
      "volume_change": -83.1314,
      "sentiment": "Neutral"
    },
    "ETHUSDT": {
      "price_change": 3.1706,
      "oi_change": 0.6534,
      "volume_change": -85.3637,
      "sentiment": "Neutral"
    },
    "BNBUSDT": {
      "price_change": 1.2636,
      "oi_change": -0.0944,
      "volume_change": -90.4302,
      "sentiment": "Neutral"
    },
    "SOLUSDT": {
      "price_change": 4.6019,
      "oi_change": 0.4291,
      "volume_change": -84.5692,
      "sentiment": "Neutral"
    },
    "DOGEUSDT": {
      "price_change": 2.1907,
      "oi_change": 0.6479,
      "volume_change": -87.9187,
      "sentiment": "Slight Bearish"
    }
  },
  "anomalies": [
    {
      "symbol": "DOGEUSDT",
      "timestamp": "2025-05-23 07:08:41",
      "data_type": "open_interest",
      "message": "Phát hiện bất thường về Open Interest cho DOGEUSDT: 1954535733.00 (Z-score: 3.02)"
    },
    {
      "symbol": "BTCUSDT",
      "timestamp": "2025-05-23 07:08:35",
      "data_type": "open_interest",
      "message": "Phát hiện bất thường về Open Interest cho BTCUSDT: 88461.98 (Z-score: 2.67)"
    },
    {
      "symbol": "BTCUSDT",
      "timestamp": "2025-05-23 06:06:41",
      "data_type": "open_interest",
      "message": "Phát hiện bất thường về Open Interest cho BTCUSDT: 88375.71 (Z-score: 2.81)"
    },
    {
      "symbol": "BTCUSDT",
      "timestamp": "2025-05-23 05:02:38",
      "data_type": "open_interest",
      "message": "Phát hiện bất thường về Open Interest cho BTCUSDT: 88411.80 (Z-score: 2.75)"
    },
    {
      "symbol": "BTCUSDT",
      "timestamp": "2025-05-23 04:02:02",
      "data_type": "open_interest",
      "message": "Phát hiện bất thường về Open Interest cho BTCUSDT: 88582.24 (Z-score: 2.81)"
    },
    {
      "symbol": "BTCUSDT",
      "timestamp": "2025-05-23 03:01:27",
      "data_type": "open_interest",
      "message": "Phát hiện bất thường về Open Interest cho BTCUSDT: 88970.01 (Z-score: 2.90)"
    },
    {
      "symbol": "BTCUSDT",
      "timestamp": "2025-05-23 00:00:00",
      "data_type": "open_interest",
      "message": "Phát hiện bất thường về Open Interest cho BTCUSDT: 88030.20 (Z-score: 3.35)"
    },
    {
      "symbol": "DOGEUSDT",
      "timestamp": "2025-05-23 00:00:00",
      "data_type": "open_interest",
      "message": "Phát hiện bất thường về Open Interest cho DOGEUSDT: 1954965094.00 (Z-score: 3.07)"
    },
    {
      "symbol": "BNBUSDT",
      "timestamp": "2025-05-22 23:59:33",
      "data_type": "open_interest",
      "message": "Phát hiện bất thường về Open Interest cho BNBUSDT: 527914.65 (Z-score: 2.56)"
    },
    {
      "symbol": "BTCUSDT",
      "timestamp": "2025-05-22 23:59:30",
      "data_type": "open_interest",
      "message": "Phát hiện bất thường về Open Interest cho BTCUSDT: 89206.88 (Z-score: 2.88)"
    },
    {
      "symbol": "BTCUSDT",
      "timestamp": "2025-05-22 23:00:00",
      "data_type": "open_interest",
      "message": "Phát hiện bất thường về Open Interest cho BTCUSDT: 88369.69 (Z-score: 2.82)"
    },
    {
      "symbol": "BTCUSDT",
      "timestamp": "2025-05-22 22:00:00",
      "data_type": "open_interest",
      "message": "Phát hiện bất thường về Open Interest cho BTCUSDT: 88417.91 (Z-score: 2.74)"
    },
    {
      "symbol": "SOLUSDT",
      "timestamp": "2025-05-22 21:17:11",
      "data_type": "open_interest",
      "message": "Phát hiện bất thường về Open Interest cho SOLUSDT: 7703541.29 (Z-score: 2.54)"
    },
    {
      "symbol": "BTCUSDT",
      "timestamp": "2025-05-22 21:00:00",
      "data_type": "open_interest",
      "message": "Phát hiện bất thường về Open Interest cho BTCUSDT: 88623.56 (Z-score: 2.74)"
    },
    {
      "symbol": "BTCUSDT",
      "timestamp": "2025-05-22 20:00:00",
      "data_type": "open_interest",
      "message": "Phát hiện bất thường về Open Interest cho BTCUSDT: 88956.11 (Z-score: 2.93)"
    },
    {
      "symbol": "SOLUSDT",
      "timestamp": "2025-05-22 19:07:48",
      "data_type": "open_interest",
      "message": "Phát hiện bất thường về Open Interest cho SOLUSDT: 7707593.63 (Z-score: 2.57)"
    },
    {
      "symbol": "ETHUSDT",
      "timestamp": "2025-05-22 19:07:45",
      "data_type": "open_interest",
      "message": "Phát hiện bất thường về Open Interest cho ETHUSDT: 1722792.73 (Z-score: 2.90)"
    },
    {
      "symbol": "DOGEUSDT",
      "timestamp": "2025-05-22 18:07:28",
      "data_type": "open_interest",
      "message": "Phát hiện bất thường về Open Interest cho DOGEUSDT: 1952009691.00 (Z-score: 2.71)"
    },
    {
      "symbol": "SOLUSDT",
      "timestamp": "2025-05-22 18:07:27",
      "data_type": "open_interest",
      "message": "Phát hiện bất thường về Open Interest cho SOLUSDT: 7703182.36 (Z-score: 2.53)"
    },
    {
      "symbol": "SOLUSDT",
      "timestamp": "2025-05-22 17:07:07",
      "data_type": "open_interest",
      "message": "Phát hiện bất thường về Open Interest cho SOLUSDT: 7700562.70 (Z-score: 2.51)"
    }
  ]
}