{
  "symbol": "ETHUSDT",
  "timestamp": "2025-05-23 19:38:13",
  "price": {
    "current": 2551.01,
    "change_percent": -3.9793
  },
  "open_interest": {
    "current": 1634283.194,
    "change_percent": -3.4874
  },
  "volume": {
    "current": 1089241.909,
    "change_percent": 294.181
  },
  "correlation": 0.5546512499374705,
  "sentiment": {
    "sentiment_score": -0.1,
    "sentiment_label": "Weak Bearish",
    "price_change": -0.5578,
    "oi_change": -3.4874,
    "volume_change": -8.8399
  }
}